README.txt
setup.py
distutils_licenses/__init__.py
distutils_licenses/command.py
distutils_licenses.egg-info/PKG-INFO
distutils_licenses.egg-info/SOURCES.txt
distutils_licenses.egg-info/dependency_links.txt
distutils_licenses.egg-info/entry_points.txt
distutils_licenses.egg-info/top_level.txt