Metadata-Version: 1.0
Name: distutils-licenses
Version: 0.1.2
Summary: adds a command to setup.py to list licenses of packages
Home-page: http://github.com/dkoepke/distutils-licenses
Author: Daniel A. Koepke
Author-email: dkoepke@gmail.com
License: MIT
Platform: UNKNOWN
